SCMeTA/__init__.py
SCMeTA/accelerate/__init__.py
SCMeTA/accelerate/mp.py
SCMeTA/accelerate/mt.py
SCMeTA/batch/__init__.py
SCMeTA/batch/calibrate.py
SCMeTA/batch/combat.py
SCMeTA/batch/numericalization.py
SCMeTA/config/__init__.py
SCMeTA/config/default.py
SCMeTA/config/load.py
SCMeTA/config/mz_filter.py
SCMeTA/core/__init__.py
SCMeTA/core/bk.py
SCMeTA/core/cluster.py
SCMeTA/core/match.py
SCMeTA/core/mpl.py
SCMeTA/file/__init__.py
SCMeTA/file/database.py
SCMeTA/file/format.py
SCMeTA/file/plugin/__init__.py
SCMeTA/file/plugin/dll/ThermoFisher.CommonCore.BackgroundSubtraction.dll
SCMeTA/file/plugin/dll/ThermoFisher.CommonCore.Data.dll
SCMeTA/file/plugin/dll/ThermoFisher.CommonCore.MassPrecisionEstimator.dll
SCMeTA/file/plugin/dll/ThermoFisher.CommonCore.RawFileReader.dll
SCMeTA/file/plugin/dll/ThermoRawFileReader.dll
SCMeTA/file/plugin/thermo_dotnet.py
SCMeTA/file/process.py
SCMeTA/file/thermo.py
SCMeTA/file/waters.py
SCMeTA/match/__init__.py
SCMeTA/match/connector.py
SCMeTA/method/__init__.py
SCMeTA/method/cell.py
SCMeTA/method/combine_mat.py
SCMeTA/method/cut.py
SCMeTA/method/fill/__init__.py
SCMeTA/method/fill/knn.py
SCMeTA/method/filter.py
SCMeTA/method/idf.py
SCMeTA/method/k_w_test.py
SCMeTA/method/machine_learning/__init__.py
SCMeTA/method/machine_learning/discriminate.py
SCMeTA/method/machine_learning/graphical_model.py
SCMeTA/method/noise.py
SCMeTA/method/normalize.py
SCMeTA/method/round.py
SCMeTA/method/to_mat.py
SCMeTA/plot/Bokeh/__init__.py
SCMeTA/plot/Bokeh/heatmap.py
SCMeTA/plot/Bokeh/range_tools.py
SCMeTA/plot/Mpl/__init__.py
SCMeTA/plot/Mpl/bar.py
SCMeTA/plot/Mpl/box.py
SCMeTA/plot/Mpl/heatmap.py
SCMeTA/plot/Mpl/line.py
SCMeTA/plot/Mpl/polygonization.py
SCMeTA/plot/Mpl/radar.py
SCMeTA/plot/Mpl/scatter.py
SCMeTA/plot/Mpl/select.py
SCMeTA/plot/Mpl/volcano.py
SCMeTA/plot/__init__.py
SCMeTA/search/__init__.py
SCMeTA/search/hmdb.py
scmeta-0.2.6.dist-info/LICENSE
scmeta-0.2.6.dist-info/METADATA
scmeta-0.2.6.dist-info/WHEEL
scmeta-0.2.6.dist-info/RECORD
